{"about.md":"a0d52820","files_javascript高级语法_bom_dom简析.md":"ac0e297b","files_javascript高级语法_iterator和generator.md":"4c00e7a0","files_javascript高级语法_json细析_浏览器数据存储.md":"9e508c27","files_javascript高级语法_javascript高级语法1.md":"f3d639ff","files_javascript高级语法_javascript高级语法2.md":"e7256d81","files_javascript高级语法_javascript高级语法3.md":"555c8804","files_javascript高级语法_javascript高级语法4.md":"60251cd0","files_javascript高级语法_promise.md":"6933bdd8","files_javascript高级语法_proxy和reflect.md":"6cdc4083","files_javascript高级语法_async_await_事件循环.md":"83499e0a","files_javascript高级语法_模块化.md":"f636b329","files_javascript高级语法_错误处理.md":"75349e31","files_webworker_javascript 工作原理之七－web workers 分类及 5 个使用场景.md":"e2a7b666","files_webworker_浅析web worker使用技巧及实战场景.md":"29fe54aa","files_css_css.md":"0dbb41a2","files_css_css怎么实现样式隔离.md":"0fd93dec","files_css_grid.md":"261ebc90","files_css_index.md":"907e12c0","files_home.md":"f218457f","files_miniprogram_index.md":"37db2592","files_nodejs_images_index.md":"a150da4e","files_nodejs_npm.md":"4d760a1f","files_nodejs_框架.md":"fd252714","files_others_arraybuffer转base64详解.md":"5b136c30","files_others_json schema.md":"9c9d2f93","files_others_multicast.md":"48fa470b","files_others_chrome.md":"66e58122","files_others_codes.md":"83e28909","files_others_index.md":"055453cd","files_others_npm.md":"0199ece2","files_others_shell.md":"b3bfe32d","files_others_vscode.md":"867e3383","files_others_yaml.md":"034ceb2a","files_others_一次搞懂数据大屏适配方案 (vw vh、rem、scale)_一次搞懂数据大屏适配方案 (vw vh、rem、scale).md":"6a95f95a","files_others_前端二进制.md":"7cbe7925","files_others_前端二进制2.md":"6fe0b6b9","files_others_前端精准计时器.md":"55dcad70","files_others_华为荣耀手机抓包配置.md":"fbde130a","files_others_多线程.md":"324ccc2d","files_others_性能.md":"8357b85e","files_others_无头浏览器puppeteer.md":"51acb32d","files_pack_webpack打包umd的export要带default访问问题.md":"0986cff6","files_pack_babel.md":"bfaba9ba","files_pack_babel6升级到babel7.md":"62581fd4","files_pack_babel之配置文件.babelrc入门详解.md":"27b83aa5","files_pack_webpack别名路径提示信息丢失问题.md":"b0de9c87","files_pack_升级webpack.md":"b3db58d5","files_pack_百分之99开发者没弄明白的babel知识.md":"dfa9e72f","files_pack_详解如何使用babel进行es6文件的编译.md":"db231a5e","files_pack_通过babel操作ast精准插入配置代码全流程.md":"a01321d3","files_practices_demo.md":"93e90b96","files_practices_threejs.md":"0b7d16da","files_react_index.md":"5d867409","files_react_依赖包.md":"cdb9e18f","files_tommyhu_cn_index.md":"7f8f6503","files_typescript_axios封装.md":"193fcf26","files_typescript_typescript通览.md":"2868d9d4","files_typescript_代码碎片.md":"c01b0972","files_typescript_项目类型声明.md":"d5ec0e82","files_vmware_docker.md":"d7966e59","files_vmware_docker实践.md":"18cd6f65","files_vmware_linux yum源问题.md":"fa658e76","files_vmware_shell.md":"a3e0286c","files_vmware_前端抢饭碗系列之docker容器编排.md":"03bd9b33","files_vmware_前端抢饭碗系列之docker进阶部署.md":"228ee9f7","files_vmware_前端抢饭碗系列之初识docker容器化部署.md":"41567179","files_vue_imgs_resolve.md":"2144b198","files_vue_vue srr如何定位客户端和服务端不一致引发问题的dom.md":"54b2f6ee","files_vue_vue2.7.md":"fb0c4966","files_vue_vue2.md":"fce0ff18","files_vue_vue3.2.md":"f04fd5a5","files_vue_vue3.md":"df0cd944","files_代码分析_ast详解与运用.md":"3073bcaf","files_代码分析_babel插件手册.md":"3870dadc","files_代码分析_babel用户手册.md":"4af57e5a","files_代码分析_index.md":"60a4bd8f","files_代码分析_编程语言的实现从ast开始.md":"9fefd89f","files_代码规范_readme.md":"df7c755f","files_低代码_index.md":"6c42ff9f","files_低代码_tmagiceditor.md":"fb1f5c9f","files_低代码_竞品分析.md":"16b212fd","files_图形图像视频_gojs.md":"61e1b8a0","files_图形图像视频_index.md":"2c56cea2","files_图形图像视频_视频处理.md":"b2c304c6","files_性能优化_指标.md":"b2b5f1e8","files_有关http_http1.1.md":"ea17ed5c","files_有关http_crlf释义.md":"b1e7a42b","files_有关http_index.md":"94e9aa05","files_算法_二分查找.md":"af712b30","files_设计模式_单例模式_单例模式.md":"d9d329db","files_设计模式_工厂方法模式_工厂方法模式.md":"292e629d","files_设计模式_工厂模式_imgs_简单工厂模式使用场景实战.md":"0a4d51a6","files_设计模式_工厂模式_工厂模式.md":"215cf28f","files_设计模式_抽象工厂模式_抽象工厂模式.md":"f2d98c36","files_设计模式_观察者模式(发布-订阅者模式或消息机制)_观察者模式.md":"51565ad1","files_设计模式_适配器模式_适配器模式.md":"c221c8cc","files_软件设计_semver.md":"0396b17f","files_软件设计_index.md":"c9caa0d8","files_软件设计_software.md":"83eaa0d7","files_软件设计_solid.md":"38dc226b","files_软件设计_代码简单设计五原则.md":"2d37b28a","files_软件设计_设计思维.md":"7e8a86b6","index.md":"1e0ba2ea"}
